./.gitignore
./.python-version
./PKG-INFO
./README.md
./events.py
./pyproject.toml
./tic_tac_toe.py
common/.gitignore
common/.python-version
common/PKG-INFO
common/README.md
common/events.py
common/pyproject.toml
common/tic_tac_toe.py
ttt_common-0.1.0.dist-info/METADATA
ttt_common-0.1.0.dist-info/WHEEL
ttt_common-0.1.0.dist-info/RECORD
