Metadata-Version: 2.4
Name: ttt-common
Version: 0.1.0
Summary: Shared functions and classes for term-tac-toe.
Author-email: Shravan Asati <dev.shravan@protonmail.com>
Requires-Python: <4,>=3.11
